[
  {"q":"Choose the correct past perfect form of the verb:\nAjay won the match although he ______ tennis before.","options":["Will not play","Have not played","Had not played","Had not been playing"],"answer":2},
  {"q":"Choose the correct option for tense:\nThe climate of the city ______ mild and pleasant most of the time.","options":["Is remaining","Is remained","Remains","Was remaining"],"answer":2},
  {"q":"I ______ (get up) at 7 every morning but today I was late.","options":["Will got up","Will get up","Get up","Got up"],"answer":2},
  {"q":"This ______ an easy quiz so far.","options":["Has been","Was","Will have been","Had been"],"answer":0},
  {"q":"Fill in the blank with the Present Perfect Continuous Tense of the verb given in bracket.\nWe ______ English for two years. (study)","options":["Had been studied","Have been studying","Have studying","Has been study"],"answer":1},
  {"q":"Choose the correct tense:\nThe phone ______ while I was having a bath.","options":["Rings","Rang","Was rang","Was ringing"],"answer":1},
  {"q":"Find the error: She is the best and beautiful girl of our village.","options":["She is the best","Of our village","And beautiful girl","No error"],"answer":2},
  {"q":"Choose the proper tense or form of the verb given in brackets:\nI ______ the painting just now. (finish)","options":["Had finished","Have finished","Finish","Finished"],"answer":1},
  {"q":"Find the error: Her goal is to win gold medal in the Asian games and made her country proud.","options":["Made her country proud.","No error","In the Asian games and","Her goal is to win gold medal"],"answer":0},
  {"q":"Choose the appropriate tense:\nThe sun ______ in the east.","options":["Rises","To rise","To rises","To rise"],"answer":0},
  {"q":"Choose the appropriate tense:\nThe judge ______ his verdict.","options":["Announced","Announce","Was announced","Is announce"],"answer":0},
  {"q":"Choose the appropriate tense:\nI ______ an apple.","options":["Call","Come","Fold","Ate"],"answer":3},
  {"q":"Identify the correct tense for the given sentence:\nI live in Model Town.","options":["Present Continuous","Future tense","Past tense","Present tense"],"answer":3},
  {"q":"Choose the appropriate tense:\nSince 2011, they ______ their son every year.","options":["Has visited","Visited","Have visited","Visit"],"answer":3},
  {"q":"Choose the correct present perfect or simple past form of the verb:\nThis house ______ to me for twenty years.","options":["Belonged","Has belonged","Belongs","Has been belonging"],"answer":1},
  {"q":"Choose the appropriate tense:\nLook! It is raining, so we can't ______ to the beach.","options":["Go","Goes","To go","Going"],"answer":0},
  {"q":"Identify the correct tense for the given sentence:\nThey ______ the mantras for an hour and are about to finish.","options":["Have recited","Recite","Are reciting","Have been reciting"],"answer":3},
  {"q":"Choose the appropriate tense:\nMy father ______ Singapore every week.","options":["Had visited","Visiting","Visits","In visit"],"answer":2},
  {"q":"Choose the proper tense or form of the verb given in brackets:\nAfter he ______ the roof ______. (leave, collapse)","options":["Had left, collapsed","Has left, collapsed","Have left, collapsed","Left, collapsed"],"answer":0},
  {"q":"I have been to Agra in January.","options":["Future Simple","Past Simple","Present Continuous","Present Perfect"],"answer":3}
]